svg_to_vl/__init__.py
svg_to_vl/__main__.py
svg_to_vl/cellmodel.py
svg_to_vl/path.py
svg_to_vl/readsvg.py
svg_to_vl-2.0.2.dist-info/METADATA
svg_to_vl-2.0.2.dist-info/WHEEL
svg_to_vl-2.0.2.dist-info/entry_points.txt
svg_to_vl-2.0.2.dist-info/top_level.txt
svg_to_vl-2.0.2.dist-info/RECORD
