Metadata-Version: 2.1
Name: svg-to-vl
Version: 2.0.2
Summary: converting cells drawn in svg files to VirtualLeaf xml start files. The svg file should be specified without extension, the resulting xml file will be stored next to the svg file.
Home-page: https://github.com/rmerks/VirtualLeaf2021/tree/v2.0.0/src/python
Author: Richard van Nieuwenhoven, Ruth Großeholz, Roeland R.M.H. Merks
Author-email: richard.nieuwenhoven@tuwien.ac.at, ruth.grosseholz@maastrichtuniversity.nl, merksrmh@math.leidenuniv.nl
License: UNKNOWN
Project-URL: Homepage, https://github.com/rmerks/VirtualLeaf2021
Keywords: virtualleaf svg conversion
Platform: UNKNOWN
Classifier: Programming Language :: Python :: 3
Classifier: License :: OSI Approved :: GNU General Public License v3 or later (GPLv3+)
Classifier: Operating System :: OS Independent
Requires-Python: >=3.1
Requires-Dist: shapely (>=1.8.0)
Requires-Dist: sympy (>=1.9)
